generators/__init__.py
generators/kotlin_generator.py
iflow_mcp_normaltusker_kotlin_mcp_server-2.1.0.dist-info/licenses/LICENSE
mcp_v3/__init__.py
mcp_v3/server/mcp_server.py
tools/__init__.py
tools/build_and_test_tool.py
tools/build_optimization.py
tools/compliance_tools.py
tools/compliance_tools_refactored.py
tools/gradle_tools.py
tools/intelligent_ai_ml_tools.py
tools/intelligent_api_integration.py
tools/intelligent_architecture.py
tools/intelligent_base.py
tools/intelligent_build_tools.py
tools/intelligent_code_tools.py
tools/intelligent_code_tools_simple.py
tools/intelligent_external_api_tools.py
tools/intelligent_file_management.py
tools/intelligent_navigation.py
tools/intelligent_navigation_tools.py
tools/intelligent_network.py
tools/intelligent_qol_dev_tools.py
tools/intelligent_refactoring.py
tools/intelligent_testing.py
tools/intelligent_tool_manager.py
tools/intelligent_ui_tools.py
tools/project_analysis.py
tools/security_hardening.py
tools/security_tools.py
utils/__init__.py
utils/input_normalizer.py
utils/placeholder_guard.py
utils/security.py
iflow_mcp_normaltusker_kotlin_mcp_server-2.1.0.dist-info/METADATA
iflow_mcp_normaltusker_kotlin_mcp_server-2.1.0.dist-info/WHEEL
iflow_mcp_normaltusker_kotlin_mcp_server-2.1.0.dist-info/entry_points.txt
iflow_mcp_normaltusker_kotlin_mcp_server-2.1.0.dist-info/top_level.txt
iflow_mcp_normaltusker_kotlin_mcp_server-2.1.0.dist-info/RECORD
