Metadata-Version: 2.4
Name: iflow-mcp_normaltusker_kotlin_mcp_server
Version: 2.1.0
Summary: Enterprise Kotlin Android MCP Server with AI-powered development tools
Author-email: normaltusker <normaltusker@users.noreply.github.com>
Maintainer-email: IFLOW <support@iflow.com>
License-Expression: MIT
Project-URL: Homepage, https://github.com/iflow-mcp/normaltusker-kotlin-mcp-server
Project-URL: Documentation, https://github.com/iflow-mcp/normaltusker-kotlin-mcp-server#readme
Project-URL: Repository, https://github.com/iflow-mcp/normaltusker-kotlin-mcp-server
Project-URL: Issues, https://github.com/iflow-mcp/normaltusker-kotlin-mcp-server/issues
Keywords: mcp,model-context-protocol,kotlin,android,development,ai,code-generation,jetpack-compose,mvvm,gradle
Classifier: Development Status :: 4 - Beta
Classifier: Intended Audience :: Developers
Classifier: Programming Language :: Python :: 3
Classifier: Programming Language :: Python :: 3.8
Classifier: Programming Language :: Python :: 3.9
Classifier: Programming Language :: Python :: 3.10
Classifier: Programming Language :: Python :: 3.11
Classifier: Programming Language :: Python :: 3.12
Classifier: Topic :: Software Development
Classifier: Topic :: Software Development :: Code Generators
Classifier: Topic :: Software Development :: Build Tools
Classifier: Operating System :: OS Independent
Requires-Python: >=3.8
License-File: LICENSE
Requires-Dist: python-dotenv>=1.0.0
Requires-Dist: pydantic>=2.0.0
Requires-Dist: mcp>=1.0.0
Requires-Dist: typing-extensions>=4.8.0
Requires-Dist: fastmcp>=2.0.0
Requires-Dist: requests>=2.31.0
Requires-Dist: cryptography>=41.0.0
Requires-Dist: bcrypt>=4.0.0
Requires-Dist: PyJWT>=2.8.0
Requires-Dist: aiosqlite>=0.19.0
Requires-Dist: sqlalchemy>=2.0.0
Requires-Dist: aiohttp>=3.8.0
Requires-Dist: httpx>=0.24.0
Requires-Dist: aiofiles>=23.0.0
Requires-Dist: watchdog>=3.0.0
Requires-Dist: Jinja2>=3.1.0
Requires-Dist: GitPython>=3.1.0
Requires-Dist: pathspec>=0.11.0
Requires-Dist: semver>=3.0.0
Requires-Dist: ruamel.yaml>=0.17.0
Requires-Dist: toml>=0.10.0
Requires-Dist: lxml>=4.9.0
Requires-Dist: chardet>=5.0.0
Requires-Dist: tzlocal>=4.0.0
Requires-Dist: psutil>=5.9.0
Provides-Extra: dev
Requires-Dist: pytest>=7.4.0; extra == "dev"
Requires-Dist: pytest-asyncio>=0.21.0; extra == "dev"
Requires-Dist: pytest-cov>=4.1.0; extra == "dev"
Requires-Dist: coverage>=7.2.0; extra == "dev"
Requires-Dist: flake8>=6.0.0; extra == "dev"
Requires-Dist: black>=23.0.0; extra == "dev"
Requires-Dist: isort>=5.12.0; extra == "dev"
Requires-Dist: pylint>=2.17.0; extra == "dev"
Requires-Dist: mypy>=1.4.0; extra == "dev"
Requires-Dist: bandit>=1.7.0; extra == "dev"
Requires-Dist: safety>=2.3.0; extra == "dev"
Requires-Dist: pre-commit>=3.3.0; extra == "dev"
Requires-Dist: tqdm>=4.65.0; extra == "dev"
Provides-Extra: ai
Requires-Dist: openai>=1.0.0; extra == "ai"
Requires-Dist: anthropic>=0.3.0; extra == "ai"
Requires-Dist: transformers>=4.30.0; extra == "ai"
Requires-Dist: torch>=2.0.0; extra == "ai"
Dynamic: license-file
